setup.cfg
setup.py
bucket_lister/__init__.py
bucket_lister.egg-info/PKG-INFO
bucket_lister.egg-info/SOURCES.txt
bucket_lister.egg-info/dependency_links.txt
bucket_lister.egg-info/requires.txt
bucket_lister.egg-info/top_level.txt