Metadata-Version: 1.1
Name: bucket-lister
Version: 0.2.2
Summary: List S3 buckets for an account
Home-page: https://github.com/chrisbarr/bilious-rutabaga
Author: Chris Barr
Author-email: chris.barr@ntlworld.com
License: UNKNOWN
Download-URL: https://github.com/chrisbarr/bilious-rutabaga/tarball/0.1
Keywords: aws,s3
Platform: UNKNOWN
